README.md
setup.py
cz_ip/__init__.py
cz_ip/__main__.py
cz_ip/ip.db
cz_ip.egg-info/PKG-INFO
cz_ip.egg-info/SOURCES.txt
cz_ip.egg-info/dependency_links.txt
cz_ip.egg-info/top_level.txt